pvdata/__init__.py
pvdata/__version__.py
pvdata/py.typed
pvdata/analytics/__init__.py
pvdata/config/__init__.py
pvdata/config/constraints.py
pvdata/config/dtype_mapper.py
pvdata/config/manager.py
pvdata/config/parquet.py
pvdata/geo/__init__.py
pvdata/geo/grid.py
pvdata/io/__init__.py
pvdata/io/batch.py
pvdata/io/operations.py
pvdata/io/reader.py
pvdata/io/writer.py
pvdata/processing/__init__.py
pvdata/processing/timeseries.py
pvdata/processing/timezone.py
pvdata/pvsystem/__init__.py
pvdata/pvsystem/constants.py
pvdata/pvsystem/core.py
pvdata/pvsystem/irradiance.py
pvdata/pvsystem/module_config.py
pvdata/pvsystem/power.py
pvdata/pvsystem/temperature.py
pvdata/pvsystem/utils.py
pvdata/query/__init__.py
pvdata/solar/__init__.py
pvdata/solar/position.py
pvdata/sources/__init__.py
pvdata/sources/nsrdb/__init__.py
pvdata/sources/nsrdb/api.py
pvdata/sources/nsrdb/datasets.py
pvdata/sources/nsrdb/pipeline.py
pvdata/utils/__init__.py
pvdata/utils/decorators.py
pvdata/utils/exceptions.py
pvdata/utils/logger.py
pvdata-0.2.1.dist-info/licenses/LICENSE
pvdata-0.2.1.dist-info/METADATA
pvdata-0.2.1.dist-info/WHEEL
pvdata-0.2.1.dist-info/top_level.txt
pvdata-0.2.1.dist-info/RECORD
