Metadata-Version: 2.4
Name: pvdata
Version: 0.2.1
Summary: High-performance toolkit for photovoltaic data processing, PV simulation, and time series analysis
Author-email: PVData Team <pvdata@example.com>
License: MIT
Project-URL: Homepage, https://github.com/pvdata/pvdata
Project-URL: Documentation, https://pvdata.readthedocs.io
Project-URL: Repository, https://github.com/pvdata/pvdata
Project-URL: Changelog, https://github.com/pvdata/pvdata/blob/main/CHANGELOG.md
Keywords: photovoltaic,solar,data,parquet,analysis,time-series,timeseries,compression,data-processing
Classifier: Development Status :: 4 - Beta
Classifier: Intended Audience :: Science/Research
Classifier: Intended Audience :: Developers
Classifier: License :: OSI Approved :: MIT License
Classifier: Operating System :: OS Independent
Classifier: Programming Language :: Python :: 3
Classifier: Programming Language :: Python :: 3.8
Classifier: Programming Language :: Python :: 3.9
Classifier: Programming Language :: Python :: 3.10
Classifier: Programming Language :: Python :: 3.11
Classifier: Programming Language :: Python :: 3.12
Classifier: Topic :: Scientific/Engineering
Classifier: Topic :: Software Development :: Libraries :: Python Modules
Classifier: Topic :: Utilities
Requires-Python: >=3.8
License-File: LICENSE
Requires-Dist: pandas>=1.5.0
Requires-Dist: pyarrow>=10.0.0
Requires-Dist: numpy>=1.21.0
Provides-Extra: dev
Requires-Dist: pytest>=7.0; extra == "dev"
Requires-Dist: pytest-cov>=4.0; extra == "dev"
Requires-Dist: black>=22.0; extra == "dev"
Requires-Dist: flake8>=5.0; extra == "dev"
Requires-Dist: mypy>=0.990; extra == "dev"
Requires-Dist: isort>=5.10; extra == "dev"
Provides-Extra: viz
Requires-Dist: matplotlib>=3.5; extra == "viz"
Requires-Dist: plotly>=5.0; extra == "viz"
Provides-Extra: sql
Requires-Dist: duckdb>=0.8.0; extra == "sql"
Provides-Extra: solar
Requires-Dist: pvlib>=0.9.0; extra == "solar"
Provides-Extra: all
Requires-Dist: pvdata[dev,solar,sql,viz]; extra == "all"
Dynamic: license-file
